Metadata-Version: 2.4
Name: first-breaks-picking
Version: 0.9.0
Summary: Project is devoted to pick waves that are the first to be detected on a seismogram with neural network
Author: Aleksei Tarasov
Author-email: Aleksei Tarasov <aleksei.v.tarasov@gmail.com>
License:                                  Apache License
Project-URL: Homepage, https://github.com/DaloroAT/first_breaks_picking
Keywords: seismic,first-breaks,computer-vision,deep-learning,segmentation,data-science
Classifier: Environment :: Console
Classifier: Environment :: X11 Applications :: Qt
Classifier: Operating System :: OS Independent
Classifier: License :: OSI Approved :: Apache Software License
Classifier: Intended Audience :: Developers
Classifier: Intended Audience :: Science/Research
Classifier: Topic :: Scientific/Engineering :: Artificial Intelligence
Classifier: Topic :: Scientific/Engineering :: Image Recognition
Classifier: Programming Language :: Python
Classifier: Programming Language :: Python :: 3.12
Classifier: Programming Language :: Python :: 3.13
Classifier: Programming Language :: Python :: 3.14
Requires-Python: >=3.12
License-File: LICENSE
Requires-Dist: requests>=2.28.2
Requires-Dist: numpy<2.0.0,>=1.24.2
Requires-Dist: pandas>=2.0.0
Requires-Dist: tqdm>=4.65.0
Requires-Dist: click>=8.1.3
Requires-Dist: pydantic>=2.0.3
Provides-Extra: engine-cpu
Requires-Dist: onnxruntime>=1.23; extra == "engine-cpu"
Provides-Extra: engine-cuda
Requires-Dist: onnxruntime-gpu[cuda,cudnn]>=1.23; extra == "engine-cuda"
Provides-Extra: engine-openvino
Requires-Dist: onnxruntime-openvino>=1.23; extra == "engine-openvino"
Requires-Dist: openvino>=2025; extra == "engine-openvino"
Provides-Extra: desktop
Requires-Dist: PyQt5>=5.15.9; extra == "desktop"
Requires-Dist: pyqtgraph>=0.13.3; extra == "desktop"
Provides-Extra: standard
Requires-Dist: onnxruntime>=1.23; extra == "standard"
Requires-Dist: PyQt5>=5.15.9; extra == "standard"
Requires-Dist: pyqtgraph>=0.13.3; extra == "standard"
Provides-Extra: dev
Requires-Dist: pre-commit; extra == "dev"
Requires-Dist: pytest; extra == "dev"
Requires-Dist: pytest-qt>=4.4.0; extra == "dev"
Dynamic: license-file
